take_ai_evaluation/__init__.py
take_ai_evaluation/domain/__init__.py
take_ai_evaluation/domain/ai_evaluation.py
take_ai_evaluation/logic/__init__.py
take_ai_evaluation/logic/intent.py
take_ai_evaluation/logic/knowledge_base.py
take_ai_evaluation/logic/utils.py
take_ai_evaluation/logic/validation.py
take_ai_evaluation/persistence/__init__.py
take_ai_evaluation/persistence/data_reader.py
take_ai_evaluation/presentation/__init__.py
take_ai_evaluation/presentation/confusion_matrix.py
take_ai_evaluation/presentation/text.py
tests/test_logic/__init__.py
tests/test_logic/test_validation.py
tests/test_persistence/__init__.py
tests/test_persistence/test_data_reader.py
take_ai_evaluation-0.2.3.dist-info/METADATA
take_ai_evaluation-0.2.3.dist-info/WHEEL
take_ai_evaluation-0.2.3.dist-info/top_level.txt
take_ai_evaluation-0.2.3.dist-info/RECORD
