Metadata-Version: 2.1
Name: take-ai-evaluation
Version: 0.2.3
Summary: Metrics and visualizations for evaluating chatbot's AI utilization.
Home-page: UNKNOWN
Author: squad ROps
Author-email: anaytics.dar@take.net
Maintainer: daresearch
Maintainer-email: anaytics.dar@take.net
License: MIT License
Keywords: ai-knowledge,chatbot,classification,evaluation
Platform: UNKNOWN
Classifier: Programming Language :: Python :: 3
Classifier: Operating System :: OS Independent
Requires-Dist: pandas
Requires-Dist: pytest
Requires-Dist: scikit-learn
Requires-Dist: matplotlib
Requires-Dist: seaborn
Requires-Dist: numpy
